sfdnormalize/__init__.py
sfdnormalize/__main__.py
sfdnormalize-1.1.1.dist-info/AUTHORS
sfdnormalize-1.1.1.dist-info/LICENSE
sfdnormalize-1.1.1.dist-info/METADATA
sfdnormalize-1.1.1.dist-info/WHEEL
sfdnormalize-1.1.1.dist-info/entry_points.txt
sfdnormalize-1.1.1.dist-info/top_level.txt
sfdnormalize-1.1.1.dist-info/RECORD
