Metadata-Version: 2.1
Name: sfdnormalize
Version: 1.1.1
Summary: Discard GUI information from SFD files
Home-page: https://github.com/alerque/sfdnormalize
Author: Caleb Maclennan
Author-email: caleb@alerque.com
Classifier: Programming Language :: Python :: 3
Classifier: License :: CC0 1.0 Universal (CC0 1.0) Public Domain Dedication
Classifier: Operating System :: OS Independent
Requires-Python: >=3.6
License-File: LICENSE
License-File: AUTHORS
